README.md
pyproject.toml
setup.cfg
setup.py
pyshewhart/__init__.py
pyshewhart/constants.py
pyshewhart/control_charts.py
pyshewhart/data_types.py
pyshewhart.egg-info/PKG-INFO
pyshewhart.egg-info/SOURCES.txt
pyshewhart.egg-info/dependency_links.txt
pyshewhart.egg-info/entry_points.txt
pyshewhart.egg-info/requires.txt
pyshewhart.egg-info/top_level.txt
pyshewhart/examples/__init__.py
pyshewhart/examples/example0.py
pyshewhart/examples/example1.py
pyshewhart/examples/example2.py
pyshewhart/examples/example3.py
pyshewhart/examples/example4.py
pyshewhart/examples/example_data_1.csv
pyshewhart/examples/example_data_2.csv