Metadata-Version: 2.1
Name: pyshewhart
Version: 1.0.1
Summary: Statistical Process Control Charts
Author: David Jonathan Huft
Author-email: jhuft@protonmail.ch
Keywords: control charts,statistical process control,SPC,quality control,manufacturing,statistics
Classifier: Development Status :: 5 - Production/Stable
Classifier: Intended Audience :: Manufacturing
Classifier: Topic :: Scientific/Engineering :: Information Analysis
Classifier: License :: OSI Approved :: MIT License
Classifier: Programming Language :: Python :: 3
Classifier: Programming Language :: Python :: 3.7
Classifier: Programming Language :: Python :: 3.8
Classifier: Programming Language :: Python :: 3.9
Classifier: Programming Language :: Python :: 3.10
Classifier: Programming Language :: Python :: 3 :: Only
Requires-Python: >=3.7, <4
Requires-Dist: matplotlib
Requires-Dist: numpy
Requires-Dist: python-dateutil
